pySymStat/Leaderboard.py
pySymStat/NUG.py
pySymStat/Partial_Solution.py
pySymStat/__init__.py
pySymStat/averaging_S2.py
pySymStat/averaging_S2_G.py
pySymStat/averaging_SO3.py
pySymStat/averaging_SO3_G.py
pySymStat/conversion.py
pySymStat/distance.py
pySymStat/meanvar.py
pySymStat/quaternion.py
pySymStat/symmetry_group.py
pySymStat/symmetry_group_Cn.py
pySymStat/symmetry_group_Dn.py
pySymStat/symmetry_group_TOI.py
pysymstat-1.3.dist-info/AUTHORS
pysymstat-1.3.dist-info/LICENSE
pysymstat-1.3.dist-info/METADATA
pysymstat-1.3.dist-info/WHEEL
pysymstat-1.3.dist-info/top_level.txt
pysymstat-1.3.dist-info/RECORD
