Metadata-Version: 2.1
Name: pysymstat
Version: 1.3
Summary: pySymStat: average orientations, including both spatial rotations and projection directions, while accounting for molecular symmetry.
Author-email: Qi Zhang <q-zhang20@mails.tsinghua.edu.cn>, Mingxu Hu <humingxu@smart.org.cn>, Chenglong Bao <clbao@tsinghua.edu.cn>
License: GNU GENERAL PUBLIC LICENSE
Project-URL: Homepage, https://github.com/mxhulab/pySymStat
Classifier: Programming Language :: Python :: 3
Classifier: License :: OSI Approved :: GNU General Public License v3 (GPLv3)
Classifier: Operating System :: OS Independent
Classifier: Environment :: GPU :: NVIDIA CUDA
Classifier: Topic :: Scientific/Engineering :: Image Processing
Requires-Python: >=3.7
License-File: LICENSE
License-File: AUTHORS
Requires-Dist: numpy >=1.18
Requires-Dist: picos >=2.4.12
